grimreaper.py
GrimReapersPie-0.1.0a2.dist-info/DESCRIPTION.rst
GrimReapersPie-0.1.0a2.dist-info/METADATA
GrimReapersPie-0.1.0a2.dist-info/metadata.json
GrimReapersPie-0.1.0a2.dist-info/RECORD
GrimReapersPie-0.1.0a2.dist-info/top_level.txt
GrimReapersPie-0.1.0a2.dist-info/WHEEL
