Metadata-Version: 2.0
Name: GrimReapersPie
Version: 0.1.0a2
Summary: Python client to the GrimReaper process killer.
Home-page: https://github.com/matee911/GrimReapersPie
Author: Mateusz Pawlik
Author-email: matee+grimreaperspie@matee.net
License: Apache 2.0
Keywords: management
Platform: UNKNOWN
Classifier: Development Status :: 3 - Alpha
Classifier: License :: OSI Approved :: Apache Software License
Classifier: Operating System :: MacOS :: MacOS X
Classifier: Operating System :: POSIX :: Linux
Classifier: Operating System :: Unix
Classifier: Intended Audience :: Developers
Classifier: Programming Language :: Python
Classifier: Programming Language :: Python :: 2.7
Classifier: Programming Language :: Python :: 3.4
Classifier: Topic :: Software Development
Classifier: Topic :: Software Development :: Libraries
Classifier: Topic :: Software Development :: Libraries :: Python Modules
Classifier: Topic :: Utilities
